{
    "@context": "https://schema.org",
    "@graph": [
      {
        "@type": "WebPage",
        "name": "Contractor Management Software",
        "url": "__SITE_URL__/contractor-management-software",
        "description": "Contractor management software for attendance, expenses, labour and project profitability.",
        "isPartOf": {
          "@type": "WebSite",
          "name": "Thekedaari",
          "url": "__SITE_URL__/"
        }
      },
      {
        "@type": "SoftwareApplication",
        "name": "Thekedaari",
        "applicationCategory": "BusinessApplication",
        "operatingSystem": "Web",
        "url": "__SITE_URL__/contractor-management-software",
        "description": "Software for contractors to manage workers, projects, expenses, site cash flow and reports.",
        "offers": {"@type": "Offer", "price": "0", "priceCurrency": "INR"}
      }
    ]
  }